lat_lon_parser/__init__.py
lat_lon_parser/lat_long.py
lat_lon_parser/parser.py
lat_lon_parser/tests/__init__.py
lat_lon_parser/tests/test_lat_lon_parser.py
lat_lon_parser/tests/test_lat_long.py
lat_lon_parser-1.3.0.dist-info/LICENSE
lat_lon_parser-1.3.0.dist-info/METADATA
lat_lon_parser-1.3.0.dist-info/WHEEL
lat_lon_parser-1.3.0.dist-info/top_level.txt
lat_lon_parser-1.3.0.dist-info/RECORD
