Metadata-Version: 2.1
Name: lat-lon-parser
Version: 1.3.0
Summary: Simple parser for latitude-longitude strings
Home-page: https://github.com/NOAA-ORR-ERD/lat_lon_parser
Author: Christopher Barker
Author-email: Chris.Barker@noaa.gov
License: UNKNOWN
Keywords: lat_lon_parser
Platform: UNKNOWN
Classifier: Development Status :: 5 - Production/Stable
Classifier: Intended Audience :: Developers
Classifier: Natural Language :: English
Classifier: Programming Language :: Python :: 2
Classifier: Programming Language :: Python :: 3
Classifier: License :: CC0 1.0 Universal (CC0 1.0) Public Domain Dedication
License-File: LICENSE
